trilogy/__init__.py
trilogy/trilogy.py
trilogy-1.0.0.dist-info/METADATA
trilogy-1.0.0.dist-info/WHEEL
trilogy-1.0.0.dist-info/licenses/LICENSE
trilogy-1.0.0.dist-info/RECORD
