Metadata-Version: 2.4
Name: trilogy
Version: 1.0.0
Summary: Python library that converts astronomical FITS images into color/grayscale images.
License: GNU GENERAL PUBLIC LICENSE
License-File: LICENSE
Keywords: fits files,astronomical images
Author: Dan Coe
Author-email: dcoe@stsci.edu
Maintainer: Renan Alves de Oliveira
Maintainer-email: fisica.renan@gmail.com
Requires-Python: >=3.11
Classifier: Programming Language :: Python :: 3
Requires-Dist: astropy (>=6.1.7)
Requires-Dist: deptry (>=0.23.1)
Requires-Dist: numpy (>=2.2.4)
Requires-Dist: pillow (>=11.2.1)
Requires-Dist: pre-commit (>=4.3.0)
Requires-Dist: scipy (>=1.15.2)
